whisper_mps-0.0.10.dist-info/METADATA
whisper_mps-0.0.10.dist-info/WHEEL
whisper_mps-0.0.10.dist-info/entry_points.txt
whisper_mps-0.0.10.dist-info/licenses/LICENSE
whisper_mps/.DS_Store
whisper_mps/__init__.py
whisper_mps/cli.py
whisper_mps/utils/__init__.py
whisper_mps/utils/ytdownloader.py
whisper_mps/whisper/__init__.py
whisper_mps/whisper/assets/download_alice.sh
whisper_mps/whisper/assets/gpt2.tiktoken
whisper_mps/whisper/assets/ls_test.flac
whisper_mps/whisper/assets/mel_filters.npz
whisper_mps/whisper/assets/multilingual.tiktoken
whisper_mps/whisper/audio.py
whisper_mps/whisper/decoding.py
whisper_mps/whisper/load_models.py
whisper_mps/whisper/timing.py
whisper_mps/whisper/tokenizer.py
whisper_mps/whisper/torch_whisper.py
whisper_mps/whisper/transcribe.py
whisper_mps/whisper/whisper.py
whisper_mps-0.0.10.dist-info/RECORD
