Metadata-Version: 2.1
Name: whisper-mps
Version: 0.0.10
Summary: with Apple MPS support for OpenAI Whisper
Author-Email: wushuhong <wushuhong@atomgradient.com>
License: MIT
Requires-Python: >=3.10
Requires-Dist: moviepy<3.0.0,>=2.0.0
Requires-Dist: pytube>=15.0.0
Requires-Dist: mlx>=0.0.5
Requires-Dist: numba>=0.58.1
Requires-Dist: numpy>=1.26.2
Requires-Dist: torch>=2.1.1
Requires-Dist: tqdm>=4.66.1
Requires-Dist: more-itertools>=10.1.0
Requires-Dist: tiktoken>=0.3.3
Requires-Dist: rich>=13.7.0
